ansys/tools/path/__init__.py
ansys/tools/path/misc.py
ansys/tools/path/path.py
ansys/tools/path/save.py
ansys/tools/path/applications/__init__.py
ansys/tools/path/applications/dyna.py
ansys/tools/path/applications/mapdl.py
ansys/tools/path/applications/mechanical.py
ansys_tools_path-0.8.1.dist-info/entry_points.txt
ansys_tools_path-0.8.1.dist-info/licenses/LICENSE
ansys_tools_path-0.8.1.dist-info/WHEEL
ansys_tools_path-0.8.1.dist-info/METADATA
ansys_tools_path-0.8.1.dist-info/RECORD
