Metadata-Version: 2.4
Name: ansys-tools-path
Version: 0.8.1
Summary: Library to locate Ansys products in a local machine.
Author-email: "ANSYS, Inc." <pyansys.core@ansys.com>
Maintainer-email: "ANSYS, Inc." <pyansys.core@ansys.com>
Requires-Python: >=3.10,<4
Classifier: Development Status :: 4 - Beta
Classifier: Programming Language :: Python :: 3.10
Classifier: Programming Language :: Python :: 3.11
Classifier: Programming Language :: Python :: 3.12
Classifier: Programming Language :: Python :: 3.13
Classifier: License :: OSI Approved :: MIT License
Classifier: Operating System :: OS Independent
License-File: LICENSE
Requires-Dist: ansys-tools-common
Requires-Dist: build==1.3.0 ; extra == "build"
Requires-Dist: twine==6.1.0 ; extra == "build"
Requires-Dist: Sphinx==8.2.3 ; extra == "doc"
Requires-Dist: ansys-sphinx-theme[autoapi]==1.5.3 ; extra == "doc"
Requires-Dist: numpydoc==1.9.0 ; extra == "doc"
Requires-Dist: sphinx-copybutton==0.5.2 ; extra == "doc"
Requires-Dist: pytest==8.4.1 ; extra == "tests"
Requires-Dist: pytest-cov==6.2.1 ; extra == "tests"
Requires-Dist: pyfakefs==5.10.2 ; extra == "tests"
Project-URL: Documentation, https://path.tools.docs.pyansys.com
Project-URL: Homepage, https://github.com/ansys/ansys-tools-path
Project-URL: Source, https://github.com/ansys/ansys-tools-path
Project-URL: Tracker, https://github.com/ansys/ansys-tools-path/issues
Provides-Extra: build
Provides-Extra: doc
Provides-Extra: tests
